{
  "project_info": {
    "project_number": "888112026414",
    "project_id": "tafs-bb6c4",
    "storage_bucket": "tafs-bb6c4.firebasestorage.app"
  },
  "client": [
    {
      "client_info": {
        "mobilesdk_app_id": "1:888112026414:android:ffbc38f61ecc24b46e60bf",
        "android_client_info": {
          "package_name": "com.tafs.app"
        }
      },
      "oauth_client": [],
      "api_key": [
        {
          "current_key": "AIzaSyB2-rmiE1ZpL3Z31mEzp4DFtGxq-gS4ROo"
        }
      ],
      "services": {
        "appinvite_service": {
          "other_platform_oauth_client": []
        }
      }
    }
  ],
  "configuration_version": "1"
}
